orange3_mlflow_export-0.6.5.dist-info/licenses/LICENSE
orangecontrib/__init__.py
orangecontrib/mlflowexport/__init__.py
orangecontrib/mlflowexport/widgets/__init__.py
orangecontrib/mlflowexport/widgets/owmlflowexport.py
orangecontrib/mlflowexport/widgets/icons/category.svg
orangecontrib/mlflowexport/widgets/icons/mywidget.svg
orange3_mlflow_export-0.6.5.dist-info/METADATA
orange3_mlflow_export-0.6.5.dist-info/WHEEL
orange3_mlflow_export-0.6.5.dist-info/entry_points.txt
orange3_mlflow_export-0.6.5.dist-info/top_level.txt
orange3_mlflow_export-0.6.5.dist-info/RECORD
