Metadata-Version: 2.4
Name: Orange3-MLflow-Export
Version: 0.6.5
Summary: Export Orange3 models with preprocessing pipelines to MLflow format for production deployment.
Home-page: https://github.com/NIRLab-com/mlflow-model-widget
Author: NIRLAB AG
Author-email: dev@nirlab.com
License: GPL-3.0-only
Project-URL: Bug Reports, https://github.com/NIRLab-com/mlflow-model-widget/issues
Project-URL: Source, https://github.com/NIRLab-com/mlflow-model-widget
Project-URL: Documentation, https://github.com/NIRLab-com/mlflow-model-widget/blob/main/README_MLFLOW_WIDGET.md
Keywords: orange3 add-on,mlflow,machine learning,model export,data science,deployment,preprocessing
Classifier: Development Status :: 4 - Beta
Classifier: Environment :: X11 Applications :: Qt
Classifier: Environment :: Plugins
Classifier: Programming Language :: Python
Classifier: Operating System :: OS Independent
Classifier: Topic :: Scientific/Engineering :: Artificial Intelligence
Classifier: Topic :: Scientific/Engineering :: Visualization
Classifier: Topic :: Software Development :: Libraries :: Python Modules
Classifier: Intended Audience :: Education
Classifier: Intended Audience :: Science/Research
Classifier: Intended Audience :: Developers
Requires-Python: >=3.8
License-File: LICENSE
Requires-Dist: Orange3
Requires-Dist: mlflow
Requires-Dist: cloudpickle
Requires-Dist: scikit-learn
Dynamic: author
Dynamic: author-email
Dynamic: classifier
Dynamic: description
Dynamic: description-content-type
Dynamic: home-page
Dynamic: keywords
Dynamic: license
Dynamic: license-file
Dynamic: project-url
Dynamic: requires-dist
Dynamic: requires-python
Dynamic: summary
